interpal/__init__.py
interpal/auth.py
interpal/client.py
interpal/exceptions.py
interpal/http.py
interpal/session_manager.py
interpal/state.py
interpal/utils.py
interpal/websocket.py
interpal/api/__init__.py
interpal/api/media.py
interpal/api/messages.py
interpal/api/notifications.py
interpal/api/posts.py
interpal/api/realtime.py
interpal/api/search.py
interpal/api/social.py
interpal/api/user.py
interpal/ext/__init__.py
interpal/ext/commands.py
interpal/models/__init__.py
interpal/models/base.py
interpal/models/events.py
interpal/models/media.py
interpal/models/message.py
interpal/models/post.py
interpal/models/social.py
interpal/models/user.py
interpal-1.2.0.dist-info/licenses/LICENSE
tests/__init__.py
tests/test_bot_extension.py
tests/test_client.py
tests/test_exceptions.py
tests/test_models.py
tests/test_utils.py
interpal-1.2.0.dist-info/METADATA
interpal-1.2.0.dist-info/WHEEL
interpal-1.2.0.dist-info/top_level.txt
interpal-1.2.0.dist-info/RECORD
