Metadata-Version: 2.4
Name: interpal
Version: 1.2.0
Summary: A comprehensive Python library for the Interpals API with sync/async support
Home-page: https://github.com/yourusername/interpal-python-lib
Author: Interpals Python Library Contributors
Author-email: 
License: MIT
Project-URL: Homepage, https://github.com/yourusername/interpal-python-lib
Project-URL: Documentation, https://github.com/yourusername/interpal-python-lib/wiki
Project-URL: Repository, https://github.com/yourusername/interpal-python-lib
Project-URL: Bug Tracker, https://github.com/yourusername/interpal-python-lib/issues
Keywords: interpals,api,client,async,websocket,social
Classifier: Development Status :: 4 - Beta
Classifier: Intended Audience :: Developers
Classifier: License :: OSI Approved :: MIT License
Classifier: Programming Language :: Python :: 3
Classifier: Programming Language :: Python :: 3.7
Classifier: Programming Language :: Python :: 3.8
Classifier: Programming Language :: Python :: 3.9
Classifier: Programming Language :: Python :: 3.10
Classifier: Programming Language :: Python :: 3.11
Classifier: Topic :: Software Development :: Libraries :: Python Modules
Classifier: Topic :: Communications :: Chat
Classifier: Topic :: Internet
Requires-Python: >=3.7
License-File: LICENSE
Requires-Dist: requests>=2.28.0
Requires-Dist: aiohttp>=3.8.0
Requires-Dist: websockets>=10.0
Provides-Extra: dev
Requires-Dist: pytest>=7.0.0; extra == "dev"
Requires-Dist: pytest-asyncio>=0.20.0; extra == "dev"
Requires-Dist: pytest-cov>=4.0.0; extra == "dev"
Requires-Dist: black>=22.0.0; extra == "dev"
Requires-Dist: flake8>=5.0.0; extra == "dev"
Requires-Dist: mypy>=0.990; extra == "dev"
Requires-Dist: isort>=5.10.0; extra == "dev"
Provides-Extra: validation
Requires-Dist: pydantic>=2.0.0; extra == "validation"
Dynamic: home-page
Dynamic: license-file
Dynamic: requires-python
